LICENSE
MANIFEST.in
README.md
dev-requirements.txt
pyproject.toml
requirements.txt
setup.py
fideslib/__init__.py
fideslib/exceptions.py
fideslib/py.typed
fideslib.egg-info/PKG-INFO
fideslib.egg-info/SOURCES.txt
fideslib.egg-info/dependency_links.txt
fideslib.egg-info/requires.txt
fideslib.egg-info/top_level.txt
fideslib/core/__init__.py
fideslib/core/config.py
fideslib/cryptography/__init__.py
fideslib/cryptography/cryptographic_util.py
fideslib/cryptography/schemas/__init__.py
fideslib/cryptography/schemas/jwt.py
fideslib/db/__init__.py
fideslib/db/base.py
fideslib/db/base_class.py
fideslib/db/session.py
fideslib/logging/__init__.py
fideslib/models/__init__.py
fideslib/models/audit_log.py
fideslib/models/client.py
fideslib/models/fides_user.py
fideslib/models/fides_user_permissions.py
fideslib/oauth/__init__.py
fideslib/oauth/jwt.py
fideslib/oauth/oauth_util.py
fideslib/oauth/privileges.py
fideslib/oauth/scopes.py
fideslib/oauth/api/__init__.py
fideslib/oauth/api/deps.py
fideslib/oauth/api/urn_registry.py
fideslib/oauth/api/routes/__init__.py
fideslib/oauth/api/routes/user_endpoints.py
fideslib/oauth/schemas/__init__.py
fideslib/oauth/schemas/oauth.py
fideslib/oauth/schemas/user.py
fideslib/oauth/schemas/user_permission.py
fideslib/schemas/__init__.py
fideslib/schemas/base_class.py
fideslib/utils/__init__.py
fideslib/utils/text.py