Metadata-Version: 2.1
Name: fideslib
Version: 3.0.2
Summary: Shared libraries, for use in any fides project.
Home-page: https://github.com/ethyca/fideslib
Author: Ethyca, Inc.
Author-email: fidesteam@ethyca.com
License: Apache License 2.0
Platform: UNKNOWN
Classifier: Development Status :: 5 - Production/Stable
Classifier: Intended Audience :: Developers
Classifier: License :: OSI Approved :: Apache Software License
Classifier: Natural Language :: English
Classifier: Programming Language :: Python :: 3 :: Only
Classifier: Programming Language :: Python :: 3.8
Classifier: Programming Language :: Python :: 3.9
Classifier: Programming Language :: Python :: 3.10
Classifier: Topic :: Software Development :: Libraries
Requires-Python: >=3.8, <4
